[
    {
        "id": "codewind-default",
        "creator": "ide",
        "name": "Codewind",
        "description": "Default Codewind Stack",
        "scope": "general",
        "tags": [
            "ws.next",
            "Theia",
            "Java",
            "JDK",
            "Node.JS",
            "NPM",
            "Yeoman"
        ],
        "components": [
            {
                "name": "Centos",
                "version": "7"
            },
            {
                "name": "OpenJDK",
                "version": "1.8.0_181"
            },
            {
                "name": "NodeJS",
                "version": "8.12.0"
            },
            {
                "name": "NPM",
                "version": "6.4.1"
            }
        ],
        "workspaceConfig": {
            "name": "che7",
            "defaultEnv": "default",
            "environments": {
                "default": {
                    "machines": {
                        "ws/dev": {
                            "attributes": {
                                "memoryLimitBytes": "536870912"
                            },
                            "servers": {},
                            "volumes": {
                                "projects": {
                                    "path": "/projects"
                                }
                            },
                            "installers": [],
                            "env": {}
                        }
                    },
                    "recipe": {
                        "type": "kubernetes",
                        "content": "kind: List\nitems:\n - \n  apiVersion: v1\n  kind: Pod\n  metadata:\n   name: ws\n  spec:\n   containers:\n    - \n     image: 'eclipse/che-dev:nightly'\n     name: dev\n     resources:\n      limits:\n       memory: 512Mi\n",
                        "contentType": "application/x-yaml"
                    }
                }
            },
            "projects": [],
            "attributes": {
                "editor": "eclipse/che-theia/next",
                "plugins": "eclipse/che-machine-exec-plugin/0.0.1,https://raw.githubusercontent.com/johnmcollier/codewind-che-plugin/PublicPlugins/plugins/codewind/codewind-sidecar/0.0.1/meta.yaml,https://raw.githubusercontent.com/johnmcollier/codewind-che-plugin/PublicPlugins/plugins/codewind/codewind-theia/0.0.1/meta.yaml"
            },
            "commands": [],
            "links": []
        },
        "stackIcon": {
            "name": "type-codewind.svg",
            "mediaType": "image/svg+xml"
        }
    }
]
